MANIFEST.in
README.md
setup.py
eSSP/__init__.py
eSSP/eSSP.py
eSSP.egg-info/PKG-INFO
eSSP.egg-info/SOURCES.txt
eSSP.egg-info/dependency_links.txt
eSSP.egg-info/requires.txt
eSSP.egg-info/top_level.txt