Metadata-Version: 1.1
Name: eSSP
Version: 1.0.0
Summary: Basic eSSP library
Home-page: https://github.com/muccc/eSSP
Author: muccc
Author-email: info@muc.ccc.de
License: ?
Platform: UNKNOWN
Classifier: Programming Language :: Python :: 2
Classifier: Intended Audience :: Developers
Classifier: Topic :: Software Development :: Libraries :: Python Modules
